Metadata-Version: 2.1
Name: rhasspy-asr
Version: 0.2.0
Summary: UNKNOWN
Home-page: https://github.com/rhasspy/rhasspy-asr
Author: Michael Hansen
Author-email: hansen.mike@gmail.com
License: UNKNOWN
Platform: UNKNOWN
Classifier: Programming Language :: Python :: 3
Classifier: License :: OSI Approved :: MIT License
Classifier: Programming Language :: Python :: 3.6
Classifier: Programming Language :: Python :: 3.7
Classifier: Programming Language :: Python :: 3.8
Requires-Python: >=3.6
